gremlin/__init__.py
gremlin/config.py
gremlin/magic.py
gremlin/registry.py
gremlin/resultset.py
gremlin/types.py
gremlin/utils.py
ipython_gremlin-1.0.0.dist-info/DESCRIPTION.rst
ipython_gremlin-1.0.0.dist-info/METADATA
ipython_gremlin-1.0.0.dist-info/RECORD
ipython_gremlin-1.0.0.dist-info/WHEEL
ipython_gremlin-1.0.0.dist-info/metadata.json
ipython_gremlin-1.0.0.dist-info/top_level.txt
