Metadata-Version: 2.0
Name: ipython-gremlin
Version: 1.0.0
Summary: Runs scripts agains the Gremlin Server from IPython
Home-page: https://github.com/davebshow/ipython-gremlin
Author: davebshow
Author-email: davebshow@gmail.com
License: MIT
Platform: UNKNOWN
Classifier: Development Status :: 3 - Alpha
Classifier: Intended Audience :: Developers
Classifier: License :: OSI Approved :: MIT License
Classifier: Operating System :: OS Independent
Classifier: Programming Language :: Python
Classifier: Programming Language :: Python :: 3
Classifier: Programming Language :: Python :: 3.4
Classifier: Programming Language :: Python :: 3 :: Only
Requires-Dist: aiogremlin (==3.2.4)
Requires-Dist: ipython (==5.3.0)
